{
  "resolvedId": "D:/projects/nuxt/workix-nuxt-front/components/Company/User/CurrentCompanyChart.vue",
  "transforms": [
    {
      "name": "vite:load-fallback",
      "result": "<script setup lang=\"ts\">\r\nimport {Chart as ChartJS, ArcElement, Tooltip, Legend, RadialLinearScale, Chart} from 'chart.js'\r\nimport {Doughnut, Pie, PolarArea} from 'vue-chartjs'\r\nimport { useColorMode } from '@vueuse/core'\r\n\r\nChartJS.register(ArcElement, Tooltip, Legend, RadialLinearScale,)\r\nChart.defaults.color = '#b6b6b6'\r\n\r\nconst chartData = ref({\r\n  labels: ['Выполненные задания', 'Выполненные IQ тесты', 'Активность', 'Посещаемость'],\r\n  datasets: [\r\n    {\r\n      backgroundColor: ['rgba(109,252,118,0.4)', \"rgba(252,155,0,0.91)\" , \"rgba(0,121,255,0.4)\", \"rgba(255,9,0,0.68)\"],\r\n      data: [70, 70, 90, 100]\r\n    }\r\n  ]\r\n});\r\n\r\nconst chartOptions = ref({\r\n  responsive: true,\r\n  maintainAspectRatio: false\r\n});\r\n</script>\r\n\r\n<template>\r\n    <PolarArea class=\"text-white\" style=\"{color: white;}\" :data=\"chartData\" :options=\"chartOptions\"></PolarArea>\r\n</template>\r\n\r\n<style scoped lang=\"scss\">\r\n\r\n</style>",
      "start": 1749796923695,
      "end": 1749796924017,
      "sourcemaps": null
    },
    {
      "name": "nuxt:layer-aliasing",
      "start": 1749796924017,
      "end": 1749796924017,
      "order": "pre"
    },
    {
      "name": "nuxt:layer-aliasing",
      "start": 1749796924017,
      "end": 1749796924017,
      "order": "pre"
    },
    {
      "name": "nuxt:server-devonly:transform",
      "start": 1749796924017,
      "end": 1749796924017,
      "order": "pre"
    },
    {
      "name": "nuxt:server-devonly:transform",
      "start": 1749796924017,
      "end": 1749796924017,
      "order": "pre"
    },
    {
      "name": "unplugin-vue-i18n",
      "start": 1749796924017,
      "end": 1749796924017,
      "order": "pre"
    },
    {
      "name": "unplugin-vue-i18n",
      "start": 1749796924017,
      "end": 1749796924017,
      "order": "pre"
    },
    {
      "name": "nuxt:client-fallback-auto-id",
      "start": 1749796924017,
      "end": 1749796924017,
      "order": "pre"
    },
    {
      "name": "vite:css",
      "start": 1749796924017,
      "end": 1749796924017,
      "order": "normal"
    },
    {
      "name": "vite:esbuild",
      "start": 1749796924017,
      "end": 1749796924017,
      "order": "normal"
    },
    {
      "name": "vite:json",
      "start": 1749796924017,
      "end": 1749796924017,
      "order": "normal"
    },
    {
      "name": "vite:worker",
      "start": 1749796924017,
      "end": 1749796924017,
      "order": "normal"
    },
    {
      "name": "vite:vue",
      "result": "import _sfc_main from \"D:/projects/nuxt/workix-nuxt-front/components/Company/User/CurrentCompanyChart.vue?vue&type=script&setup=true&lang.ts\";\nexport * from \"D:/projects/nuxt/workix-nuxt-front/components/Company/User/CurrentCompanyChart.vue?vue&type=script&setup=true&lang.ts\";\nimport { useSSRContext as __vite_useSSRContext } from \"vue\";\nconst _sfc_setup = _sfc_main.setup;\n_sfc_main.setup = (props, ctx) => {\n  const ssrContext = __vite_useSSRContext();\n  (ssrContext.modules || (ssrContext.modules = /* @__PURE__ */ new Set())).add(\"components/Company/User/CurrentCompanyChart.vue\");\n  return _sfc_setup ? _sfc_setup(props, ctx) : void 0;\n};\nexport default _sfc_main;\n",
      "start": 1749796924017,
      "end": 1749796924383,
      "order": "normal",
      "sourcemaps": {
        "mappings": ""
      }
    },
    {
      "name": "vite:vue-jsx",
      "start": 1749796924383,
      "end": 1749796924383,
      "order": "normal"
    },
    {
      "name": "replace",
      "start": 1749796924383,
      "end": 1749796924383,
      "order": "normal"
    },
    {
      "name": "replace",
      "start": 1749796924383,
      "end": 1749796924383,
      "order": "normal"
    },
    {
      "name": "nuxt:remove-plugin-metadata",
      "start": 1749796924384,
      "end": 1749796924384,
      "order": "normal"
    },
    {
      "name": "nuxt:remove-plugin-metadata",
      "start": 1749796924384,
      "end": 1749796924384,
      "order": "normal"
    },
    {
      "name": "nuxt:components:imports",
      "start": 1749796924384,
      "end": 1749796924384,
      "order": "normal"
    },
    {
      "name": "replace",
      "start": 1749796924384,
      "end": 1749796924384,
      "order": "normal"
    },
    {
      "name": "ssr-styles",
      "start": 1749796924385,
      "end": 1749796924385,
      "order": "normal"
    },
    {
      "name": "vite:define",
      "start": 1749796924385,
      "end": 1749796924385,
      "order": "normal"
    },
    {
      "name": "vite:css-post",
      "start": 1749796924385,
      "end": 1749796924385,
      "order": "normal"
    },
    {
      "name": "vite:build-html",
      "start": 1749796924385,
      "end": 1749796924385,
      "order": "normal"
    },
    {
      "name": "vite:worker-import-meta-url",
      "start": 1749796924387,
      "end": 1749796924388,
      "order": "normal"
    },
    {
      "name": "vite:asset-import-meta-url",
      "start": 1749796924389,
      "end": 1749796924390,
      "order": "normal"
    },
    {
      "name": "commonjs",
      "start": 1749796924392,
      "end": 1749796924392,
      "order": "normal"
    },
    {
      "name": "vite:dynamic-import-vars",
      "start": 1749796924400,
      "end": 1749796924401,
      "order": "normal"
    },
    {
      "name": "vite:import-glob",
      "start": 1749796924404,
      "end": 1749796924409,
      "order": "normal"
    },
    {
      "name": "nuxt:composable-keys",
      "start": 1749796924410,
      "end": 1749796924410,
      "order": "post"
    },
    {
      "name": "nuxt:composable-keys",
      "start": 1749796924410,
      "end": 1749796924410,
      "order": "post"
    },
    {
      "name": "nuxtjs:i18n-macros-transform",
      "start": 1749796924411,
      "end": 1749796924411,
      "order": "post"
    },
    {
      "name": "nuxtjs:i18n-macros-transform",
      "start": 1749796924411,
      "end": 1749796924411,
      "order": "post"
    },
    {
      "name": "nuxtjs:i18n-resource",
      "start": 1749796924411,
      "end": 1749796924411,
      "order": "post"
    },
    {
      "name": "nuxtjs:i18n-resource",
      "start": 1749796924411,
      "end": 1749796924411,
      "order": "post"
    },
    {
      "name": "nuxtjs:i18n-meta-deprecation",
      "start": 1749796924412,
      "end": 1749796924413,
      "order": "post"
    },
    {
      "name": "nuxtjs:i18n-meta-deprecation",
      "start": 1749796924412,
      "end": 1749796924413,
      "order": "post"
    },
    {
      "name": "nuxt:imports-transform",
      "start": 1749796924414,
      "end": 1749796924416,
      "order": "post"
    },
    {
      "name": "nuxt:imports-transform",
      "start": 1749796924414,
      "end": 1749796924416,
      "order": "post"
    },
    {
      "name": "unctx:transform",
      "start": 1749796924416,
      "end": 1749796924416,
      "order": "post"
    },
    {
      "name": "unctx:transform",
      "start": 1749796924416,
      "end": 1749796924416,
      "order": "post"
    },
    {
      "name": "nuxt:pages-macros-transform",
      "start": 1749796924419,
      "end": 1749796924419,
      "order": "post"
    },
    {
      "name": "nuxt:pages-macros-transform",
      "start": 1749796924419,
      "end": 1749796924419,
      "order": "post"
    },
    {
      "name": "nuxt:tree-shake-template",
      "start": 1749796924420,
      "end": 1749796924420,
      "order": "post"
    },
    {
      "name": "nuxt:components-loader",
      "start": 1749796924420,
      "end": 1749796924420,
      "order": "post"
    },
    {
      "name": "nuxt:tree-shake-composables:transform",
      "start": 1749796924420,
      "end": 1749796924420,
      "order": "post"
    },
    {
      "name": "vite:build-import-analysis",
      "start": 1749796924420,
      "end": 1749796924420,
      "order": "normal"
    },
    {
      "name": "vite:reporter",
      "start": 1749796924421,
      "end": 1749796924421,
      "order": "normal"
    }
  ]
}
