{
  "resolvedId": "D:/projects/nuxt/workix-nuxt-front/components/Cloud/CloudUI/CloudUIStructure/TheCloudUIStructureFolder.vue?vue&type=script&setup=true&lang.tsx",
  "transforms": [
    {
      "name": "vite:vue",
      "result": "import { defineComponent as _defineComponent } from 'vue'\nimport { renderSlot as _renderSlot, createElementVNode as _createElementVNode, openBlock as _openBlock, createElementBlock as _createElementBlock } from \"vue\"\n\nconst _hoisted_1 = { class: \"p-2 flex items-center gap-x-4 hover:bg-gray-700 transition-all duration-200 cursor-pointer rounded-lg\" }\nconst _hoisted_2 = { class: \"tracking-widest text-sm\" }\n\nimport {useCloudStore} from \"~/stores/cloud\";\nimport TheCloudUIStructureSubFolder from \"~/components/Cloud/CloudUI/CloudUIStructure/TheCloudUIStructureSubFolder.vue\";\n\n\nexport default /*#__PURE__*/_defineComponent({\n  __name: 'TheCloudUIStructureFolder',\n  props: {\n  showFolder: {\n    type: Object,\n    default: () => {\n    },\n  },\n},\n  setup(__props) {\n\n\n\nreturn (_ctx: any,_cache: any) => {\n  return (_openBlock(), _createElementBlock(\"div\", _hoisted_1, [\n    _createElementVNode(\"div\", null, [\n      _renderSlot(_ctx.$slots, \"structureSvg\")\n    ]),\n    _createElementVNode(\"p\", _hoisted_2, [\n      _renderSlot(_ctx.$slots, \"structureName\")\n    ])\n  ]))\n}\n}\n\n})",
      "start": 1741686093918,
      "end": 1741686093918
    },
    {
      "name": "nuxt:layer-aliasing",
      "start": 1741686093918,
      "end": 1741686093918,
      "order": "pre"
    },
    {
      "name": "nuxt:server-devonly:transform",
      "start": 1741686093918,
      "end": 1741686093919,
      "order": "pre"
    },
    {
      "name": "unplugin-vue-i18n",
      "start": 1741686093919,
      "end": 1741686093919,
      "order": "pre"
    },
    {
      "name": "nuxt:client-fallback-auto-id",
      "start": 1741686093919,
      "end": 1741686093919,
      "order": "pre"
    },
    {
      "name": "vite:css",
      "start": 1741686093922,
      "end": 1741686093922,
      "order": "normal"
    },
    {
      "name": "vite:esbuild",
      "start": 1741686093922,
      "end": 1741686093922,
      "order": "normal"
    },
    {
      "name": "vite:json",
      "start": 1741686093922,
      "end": 1741686093922,
      "order": "normal"
    },
    {
      "name": "vite:worker",
      "start": 1741686093922,
      "end": 1741686093922,
      "order": "normal"
    },
    {
      "name": "vite:vue",
      "start": 1741686093922,
      "end": 1741686093922,
      "order": "normal"
    },
    {
      "name": "vite:vue-jsx",
      "result": "import { defineComponent as _defineComponent } from 'vue';\nimport { renderSlot as _renderSlot, createElementVNode as _createElementVNode, openBlock as _openBlock, createElementBlock as _createElementBlock } from \"vue\";\nconst _hoisted_1 = {\n  class: \"p-2 flex items-center gap-x-4 hover:bg-gray-700 transition-all duration-200 cursor-pointer rounded-lg\"\n};\nconst _hoisted_2 = {\n  class: \"tracking-widest text-sm\"\n};\nexport default /*#__PURE__*/_defineComponent({\n  __name: 'TheCloudUIStructureFolder',\n  props: {\n    showFolder: {\n      type: Object,\n      default: () => {}\n    }\n  },\n  setup(__props) {\n    return (_ctx, _cache) => {\n      return _openBlock(), _createElementBlock(\"div\", _hoisted_1, [_createElementVNode(\"div\", null, [_renderSlot(_ctx.$slots, \"structureSvg\")]), _createElementVNode(\"p\", _hoisted_2, [_renderSlot(_ctx.$slots, \"structureName\")])]);\n    };\n  }\n});",
      "start": 1741686093922,
      "end": 1741686094046,
      "order": "normal",
      "sourcemaps": null
    },
    {
      "name": "replace",
      "start": 1741686094046,
      "end": 1741686094046,
      "order": "normal"
    },
    {
      "name": "nuxt:remove-plugin-metadata",
      "start": 1741686094046,
      "end": 1741686094046,
      "order": "normal"
    },
    {
      "name": "nuxt:chunk-error",
      "start": 1741686094046,
      "end": 1741686094046,
      "order": "normal"
    },
    {
      "name": "nuxt:components:imports",
      "start": 1741686094046,
      "end": 1741686094046,
      "order": "normal"
    },
    {
      "name": "replace",
      "start": 1741686094047,
      "end": 1741686094047,
      "order": "normal"
    },
    {
      "name": "ssr-styles",
      "start": 1741686094047,
      "end": 1741686094047,
      "order": "normal"
    },
    {
      "name": "vite:define",
      "start": 1741686094047,
      "end": 1741686094047,
      "order": "normal"
    },
    {
      "name": "vite:css-post",
      "start": 1741686094047,
      "end": 1741686094047,
      "order": "normal"
    },
    {
      "name": "vite:build-html",
      "start": 1741686094047,
      "end": 1741686094047,
      "order": "normal"
    },
    {
      "name": "vite:worker-import-meta-url",
      "start": 1741686094047,
      "end": 1741686094047,
      "order": "normal"
    },
    {
      "name": "vite:asset-import-meta-url",
      "start": 1741686094047,
      "end": 1741686094047,
      "order": "normal"
    },
    {
      "name": "commonjs",
      "start": 1741686094048,
      "end": 1741686094048,
      "order": "normal"
    },
    {
      "name": "vite:dynamic-import-vars",
      "start": 1741686094048,
      "end": 1741686094048,
      "order": "normal"
    },
    {
      "name": "vite:import-glob",
      "start": 1741686094048,
      "end": 1741686094048,
      "order": "normal"
    },
    {
      "name": "nuxt:composable-keys",
      "start": 1741686094048,
      "end": 1741686094048,
      "order": "post"
    },
    {
      "name": "nuxtjs:i18n-macros-transform",
      "start": 1741686094048,
      "end": 1741686094048,
      "order": "post"
    },
    {
      "name": "nuxtjs:i18n-resource",
      "start": 1741686094048,
      "end": 1741686094048,
      "order": "post"
    },
    {
      "name": "nuxtjs:i18n-meta-deprecation",
      "start": 1741686094048,
      "end": 1741686094048,
      "order": "post"
    },
    {
      "name": "nuxt:imports-transform",
      "start": 1741686094048,
      "end": 1741686094049,
      "order": "post"
    },
    {
      "name": "unctx:transform",
      "start": 1741686094049,
      "end": 1741686094049,
      "order": "post"
    },
    {
      "name": "nuxt:pages-macros-transform",
      "start": 1741686094049,
      "end": 1741686094049,
      "order": "post"
    },
    {
      "name": "nuxt:runtime-paths-dep",
      "start": 1741686094049,
      "end": 1741686094049,
      "order": "post"
    },
    {
      "name": "nuxt:route-injection-plugin",
      "start": 1741686094049,
      "end": 1741686094049,
      "order": "post"
    },
    {
      "name": "nuxt:components-loader",
      "start": 1741686094049,
      "end": 1741686094049,
      "order": "post"
    },
    {
      "name": "nuxt:tree-shake-composables:transform",
      "start": 1741686094049,
      "end": 1741686094049,
      "order": "post"
    },
    {
      "name": "vite:build-import-analysis",
      "start": 1741686094049,
      "end": 1741686094049,
      "order": "normal"
    },
    {
      "name": "vite:reporter",
      "start": 1741686094049,
      "end": 1741686094049,
      "order": "normal"
    }
  ]
}
