{
  "resolvedId": "D:/projects/nuxt/workix-nuxt-front/components/Company/admin/CompanyList.vue",
  "transforms": [
    {
      "name": "vite:load-fallback",
      "result": "<script setup lang=\"ts\">\ndefineProps({\n  companyBlock: {\n    type: Object,\n    required: true,\n    default: () => {\n    }\n  }\n})\n\n</script>\n\n<template>\n  <div>\n    <NuxtLink :to=\"`/base/companies/${companyBlock.id}`\"\n              class=\"transition-all cursor-pointer dark:bg-gray-400 dark:hover:bg-gray-300 dark:shadow-none shadow-xl hover:bg-gray-100 dark:border-none border-t border-t-gray-100 p-4 rounded-xl flex items-center gap-x-4 \">\n      <img v-if=\"companyBlock.logo\" class=\"w-[50px] h-[50px] rounded-full\" :src=\"companyBlock.logo.replace(/\\/png/g, '/webp')\" alt=\"\">\n      <h1 class=\"tracking-widest\">{{ companyBlock.name }}</h1>\n    </NuxtLink>\n  </div>\n</template>\n\n<style scoped lang=\"scss\">\n\n</style>",
      "start": 1743013001217,
      "end": 1743013001554,
      "sourcemaps": null
    },
    {
      "name": "nuxt:layer-aliasing",
      "start": 1743013001554,
      "end": 1743013001554,
      "order": "pre"
    },
    {
      "name": "nuxt:server-devonly:transform",
      "start": 1743013001554,
      "end": 1743013001554,
      "order": "pre"
    },
    {
      "name": "unplugin-vue-i18n",
      "start": 1743013001555,
      "end": 1743013001555,
      "order": "pre"
    },
    {
      "name": "nuxt:client-fallback-auto-id",
      "start": 1743013001555,
      "end": 1743013001555,
      "order": "pre"
    },
    {
      "name": "vite:css",
      "start": 1743013001555,
      "end": 1743013001555,
      "order": "normal"
    },
    {
      "name": "vite:esbuild",
      "start": 1743013001555,
      "end": 1743013001555,
      "order": "normal"
    },
    {
      "name": "vite:json",
      "start": 1743013001555,
      "end": 1743013001555,
      "order": "normal"
    },
    {
      "name": "vite:worker",
      "start": 1743013001555,
      "end": 1743013001555,
      "order": "normal"
    },
    {
      "name": "vite:vue",
      "result": "import _sfc_main from \"D:/projects/nuxt/workix-nuxt-front/components/Company/admin/CompanyList.vue?vue&type=script&setup=true&lang.ts\";\nexport * from \"D:/projects/nuxt/workix-nuxt-front/components/Company/admin/CompanyList.vue?vue&type=script&setup=true&lang.ts\";\nexport default _sfc_main;\n",
      "start": 1743013001555,
      "end": 1743013004116,
      "order": "normal",
      "sourcemaps": {
        "mappings": ""
      }
    },
    {
      "name": "vite:vue-jsx",
      "start": 1743013004117,
      "end": 1743013004117,
      "order": "normal"
    },
    {
      "name": "replace",
      "start": 1743013004118,
      "end": 1743013004118,
      "order": "normal"
    },
    {
      "name": "nuxt:remove-plugin-metadata",
      "start": 1743013004118,
      "end": 1743013004118,
      "order": "normal"
    },
    {
      "name": "nuxt:chunk-error",
      "start": 1743013004119,
      "end": 1743013004119,
      "order": "normal"
    },
    {
      "name": "nuxt:components:imports",
      "start": 1743013004119,
      "end": 1743013004120,
      "order": "normal"
    },
    {
      "name": "replace",
      "start": 1743013004120,
      "end": 1743013004120,
      "order": "normal"
    },
    {
      "name": "ssr-styles",
      "start": 1743013004121,
      "end": 1743013004121,
      "order": "normal"
    },
    {
      "name": "vite:define",
      "start": 1743013004121,
      "end": 1743013004121,
      "order": "normal"
    },
    {
      "name": "vite:css-post",
      "start": 1743013004121,
      "end": 1743013004122,
      "order": "normal"
    },
    {
      "name": "vite:build-html",
      "start": 1743013004122,
      "end": 1743013004122,
      "order": "normal"
    },
    {
      "name": "vite:worker-import-meta-url",
      "start": 1743013004122,
      "end": 1743013004122,
      "order": "normal"
    },
    {
      "name": "vite:asset-import-meta-url",
      "start": 1743013004122,
      "end": 1743013004123,
      "order": "normal"
    },
    {
      "name": "commonjs",
      "start": 1743013004126,
      "end": 1743013004126,
      "order": "normal"
    },
    {
      "name": "vite:dynamic-import-vars",
      "start": 1743013004127,
      "end": 1743013004127,
      "order": "normal"
    },
    {
      "name": "vite:import-glob",
      "start": 1743013004127,
      "end": 1743013004127,
      "order": "normal"
    },
    {
      "name": "nuxt:composable-keys",
      "start": 1743013004129,
      "end": 1743013004129,
      "order": "post"
    },
    {
      "name": "nuxtjs:i18n-macros-transform",
      "start": 1743013004130,
      "end": 1743013004131,
      "order": "post"
    },
    {
      "name": "nuxtjs:i18n-resource",
      "start": 1743013004131,
      "end": 1743013004132,
      "order": "post"
    },
    {
      "name": "nuxtjs:i18n-meta-deprecation",
      "start": 1743013004132,
      "end": 1743013004133,
      "order": "post"
    },
    {
      "name": "nuxt:imports-transform",
      "start": 1743013004133,
      "end": 1743013004141,
      "order": "post"
    },
    {
      "name": "unctx:transform",
      "start": 1743013004141,
      "end": 1743013004141,
      "order": "post"
    },
    {
      "name": "nuxt:pages-macros-transform",
      "start": 1743013004143,
      "end": 1743013004143,
      "order": "post"
    },
    {
      "name": "nuxt:runtime-paths-dep",
      "start": 1743013004147,
      "end": 1743013004147,
      "order": "post"
    },
    {
      "name": "nuxt:route-injection-plugin",
      "start": 1743013004150,
      "end": 1743013004150,
      "order": "post"
    },
    {
      "name": "nuxt:components-loader",
      "start": 1743013004152,
      "end": 1743013004153,
      "order": "post"
    },
    {
      "name": "nuxt:tree-shake-composables:transform",
      "start": 1743013004153,
      "end": 1743013004153,
      "order": "post"
    },
    {
      "name": "vite:build-import-analysis",
      "start": 1743013004154,
      "end": 1743013004155,
      "order": "normal"
    },
    {
      "name": "vite:reporter",
      "start": 1743013004155,
      "end": 1743013004155,
      "order": "normal"
    }
  ]
}
