{
  "resolvedId": "D:/projects/nuxt/workix-nuxt-front/node_modules/lodash/_arrayFilter.js",
  "transforms": [
    {
      "name": "vite:load-fallback",
      "result": "/**\n * A specialized version of `_.filter` for arrays without support for\n * iteratee shorthands.\n *\n * @private\n * @param {Array} [array] The array to iterate over.\n * @param {Function} predicate The function invoked per iteration.\n * @returns {Array} Returns the new filtered array.\n */\nfunction arrayFilter(array, predicate) {\n  var index = -1,\n      length = array == null ? 0 : array.length,\n      resIndex = 0,\n      result = [];\n\n  while (++index < length) {\n    var value = array[index];\n    if (predicate(value, index, array)) {\n      result[resIndex++] = value;\n    }\n  }\n  return result;\n}\n\nmodule.exports = arrayFilter;\n",
      "start": 1750751983719,
      "end": 1750751983753,
      "sourcemaps": null
    },
    {
      "name": "nuxt:layer-aliasing",
      "start": 1750751983753,
      "end": 1750751983753,
      "order": "pre"
    },
    {
      "name": "nuxt:server-devonly:transform",
      "start": 1750751983753,
      "end": 1750751983753,
      "order": "pre"
    },
    {
      "name": "unplugin-vue-i18n",
      "start": 1750751983753,
      "end": 1750751983753,
      "order": "pre"
    },
    {
      "name": "nuxt:client-fallback-auto-id",
      "start": 1750751983753,
      "end": 1750751983753,
      "order": "pre"
    },
    {
      "name": "vite:css",
      "start": 1750751983753,
      "end": 1750751983753,
      "order": "normal"
    },
    {
      "name": "vite:esbuild",
      "start": 1750751983753,
      "end": 1750751983753,
      "order": "normal"
    },
    {
      "name": "vite:json",
      "start": 1750751983753,
      "end": 1750751983753,
      "order": "normal"
    },
    {
      "name": "vite:worker",
      "start": 1750751983753,
      "end": 1750751983753,
      "order": "normal"
    },
    {
      "name": "vite:vue",
      "start": 1750751983753,
      "end": 1750751983753,
      "order": "normal"
    },
    {
      "name": "vite:vue-jsx",
      "start": 1750751983753,
      "end": 1750751983753,
      "order": "normal"
    },
    {
      "name": "replace",
      "start": 1750751983753,
      "end": 1750751983753,
      "order": "normal"
    },
    {
      "name": "nuxt:remove-plugin-metadata",
      "start": 1750751983753,
      "end": 1750751983753,
      "order": "normal"
    },
    {
      "name": "nuxt:chunk-error",
      "start": 1750751983753,
      "end": 1750751983753,
      "order": "normal"
    },
    {
      "name": "nuxt:components:imports",
      "start": 1750751983753,
      "end": 1750751983754,
      "order": "normal"
    },
    {
      "name": "replace",
      "start": 1750751983754,
      "end": 1750751983754,
      "order": "normal"
    },
    {
      "name": "ssr-styles",
      "start": 1750751983754,
      "end": 1750751983754,
      "order": "normal"
    },
    {
      "name": "vite:define",
      "start": 1750751983754,
      "end": 1750751983754,
      "order": "normal"
    },
    {
      "name": "vite:css-post",
      "start": 1750751983754,
      "end": 1750751983754,
      "order": "normal"
    },
    {
      "name": "vite:build-html",
      "start": 1750751983754,
      "end": 1750751983754,
      "order": "normal"
    },
    {
      "name": "vite:worker-import-meta-url",
      "start": 1750751983754,
      "end": 1750751983754,
      "order": "normal"
    },
    {
      "name": "vite:asset-import-meta-url",
      "start": 1750751983754,
      "end": 1750751983754,
      "order": "normal"
    },
    {
      "name": "commonjs",
      "result": "/**\n * A specialized version of `_.filter` for arrays without support for\n * iteratee shorthands.\n *\n * @private\n * @param {Array} [array] The array to iterate over.\n * @param {Function} predicate The function invoked per iteration.\n * @returns {Array} Returns the new filtered array.\n */\nimport * as commonjsHelpers from \"\u0000commonjsHelpers.js\";\n\nfunction arrayFilter(array, predicate) {\n  var index = -1,\n      length = array == null ? 0 : array.length,\n      resIndex = 0,\n      result = [];\n\n  while (++index < length) {\n    var value = array[index];\n    if (predicate(value, index, array)) {\n      result[resIndex++] = value;\n    }\n  }\n  return result;\n}\n\nvar _arrayFilter = arrayFilter;\n\nexport default /*@__PURE__*/commonjsHelpers.getDefaultExportFromCjs(_arrayFilter);\nexport { _arrayFilter as __moduleExports };",
      "start": 1750751983754,
      "end": 1750751983754,
      "order": "normal",
      "sourcemaps": {
        "version": 3,
        "sources": [
          ""
        ],
        "names": [],
        "mappings": ";;;;;;;;;;;AASA,SAAS,WAAW,CAAC,KAAK,EAAE,SAAS,EAAE;AACvC,EAAE,IAAI,KAAK,GAAG,CAAC,CAAC;AAChB,MAAM,MAAM,GAAG,KAAK,IAAI,IAAI,GAAG,CAAC,GAAG,KAAK,CAAC,MAAM;AAC/C,MAAM,QAAQ,GAAG,CAAC;AAClB,MAAM,MAAM,GAAG,EAAE,CAAC;AAClB;AACA,EAAE,OAAO,EAAE,KAAK,GAAG,MAAM,EAAE;AAC3B,IAAI,IAAI,KAAK,GAAG,KAAK,CAAC,KAAK,CAAC,CAAC;AAC7B,IAAI,IAAI,SAAS,CAAC,KAAK,EAAE,KAAK,EAAE,KAAK,CAAC,EAAE;AACxC,MAAM,MAAM,CAAC,QAAQ,EAAE,CAAC,GAAG,KAAK,CAAC;AACjC,KAAK;AACL,GAAG;AACH,EAAE,OAAO,MAAM,CAAC;AAChB,CAAC;AACD;IACA,YAAc,GAAG,WAAW"
      }
    },
    {
      "name": "vite:dynamic-import-vars",
      "start": 1750751983754,
      "end": 1750751983754,
      "order": "normal"
    },
    {
      "name": "vite:import-glob",
      "start": 1750751983754,
      "end": 1750751983754,
      "order": "normal"
    },
    {
      "name": "nuxt:composable-keys",
      "start": 1750751983754,
      "end": 1750751983754,
      "order": "post"
    },
    {
      "name": "nuxtjs:i18n-macros-transform",
      "start": 1750751983754,
      "end": 1750751983754,
      "order": "post"
    },
    {
      "name": "nuxtjs:i18n-resource",
      "start": 1750751983754,
      "end": 1750751983754,
      "order": "post"
    },
    {
      "name": "nuxtjs:i18n-meta-deprecation",
      "start": 1750751983754,
      "end": 1750751983754,
      "order": "post"
    },
    {
      "name": "nuxt:imports-transform",
      "start": 1750751983754,
      "end": 1750751983754,
      "order": "post"
    },
    {
      "name": "unctx:transform",
      "start": 1750751983755,
      "end": 1750751983755,
      "order": "post"
    },
    {
      "name": "nuxt:pages-macros-transform",
      "start": 1750751983755,
      "end": 1750751983755,
      "order": "post"
    },
    {
      "name": "nuxt:runtime-paths-dep",
      "start": 1750751983755,
      "end": 1750751983755,
      "order": "post"
    },
    {
      "name": "nuxt:route-injection-plugin",
      "start": 1750751983755,
      "end": 1750751983755,
      "order": "post"
    },
    {
      "name": "nuxt:components-loader",
      "start": 1750751983755,
      "end": 1750751983755,
      "order": "post"
    },
    {
      "name": "nuxt:tree-shake-composables:transform",
      "start": 1750751983755,
      "end": 1750751983755,
      "order": "post"
    },
    {
      "name": "vite:build-import-analysis",
      "start": 1750751983755,
      "end": 1750751983755,
      "order": "normal"
    },
    {
      "name": "vite:reporter",
      "start": 1750751983755,
      "end": 1750751983755,
      "order": "normal"
    }
  ]
}
